Metadata-Version: 1.0
Name: vibe
Version: 1.2.0
Summary: Python Package for Vibe, Fastest way to know everything about your contacts
Home-page: https://github.com/sachinvettithanam/vibe
Author: Sachin Philip Mathew
Author-email: sachinvettithanam@gmail.com
License: MIT
Keywords: vibe
Platform: UNKNOWN
